google/cloud/dns/__init__.py
google/cloud/dns/_http.py
google/cloud/dns/changes.py
google/cloud/dns/client.py
google/cloud/dns/resource_record_set.py
google/cloud/dns/version.py
google/cloud/dns/zone.py
google_cloud_dns-0.36.0.dist-info/licenses/LICENSE
google_cloud_dns-0.36.0.dist-info/METADATA
google_cloud_dns-0.36.0.dist-info/WHEEL
google_cloud_dns-0.36.0.dist-info/top_level.txt
google_cloud_dns-0.36.0.dist-info/RECORD
